{
  "kind": "collectionType",
  "collectionName": "menu_links",
  "info": {
    "singularName": "menu-link",
    "pluralName": "menu-links",
    "displayName": "MenuLinks"
  },
  "options": {
    "draftAndPublish": false
  },
  "pluginOptions": {
    "i18n": {
      "localized": true
    }
  },
  "attributes": {
    "label": {
      "pluginOptions": {
        "i18n": {
          "localized": true
        }
      },
      "type": "string",
      "required": true
    },
    "slug": {
      "pluginOptions": {
        "i18n": {
          "localized": true
        }
      },
      "type": "uid",
      "targetField": "label",
      "required": true
    }
  }
}
